CHANGES.rst
COPYING
LICENSE
MANIFEST.in
README.rst
setup.py
Foundations.egg-info/PKG-INFO
Foundations.egg-info/SOURCES.txt
Foundations.egg-info/dependency_links.txt
Foundations.egg-info/requires.txt
Foundations.egg-info/top_level.txt
docs/help/Foundations_Manual.html
docs/help/Foundations_Manual.rst
docs/sphinx/Makefile
docs/sphinx/build/doctrees/environment.pickle
docs/sphinx/build/doctrees/index.doctree
docs/sphinx/build/doctrees/resources/pages/about.doctree
docs/sphinx/build/doctrees/resources/pages/api.doctree
docs/sphinx/build/doctrees/resources/pages/changes.doctree
docs/sphinx/build/doctrees/resources/pages/installation.doctree
docs/sphinx/build/doctrees/resources/pages/introduction.doctree
docs/sphinx/build/doctrees/resources/pages/usage.doctree
docs/sphinx/build/doctrees/resources/pages/api/foundations.cache.doctree
docs/sphinx/build/doctrees/resources/pages/api/foundations.common.doctree
docs/sphinx/build/doctrees/resources/pages/api/foundations.core.doctree
docs/sphinx/build/doctrees/resources/pages/api/foundations.dataStructures.doctree
docs/sphinx/build/doctrees/resources/pages/api/foundations.decorators.doctree
docs/sphinx/build/doctrees/resources/pages/api/foundations.environment.doctree
docs/sphinx/build/doctrees/resources/pages/api/foundations.exceptions.doctree
docs/sphinx/build/doctrees/resources/pages/api/foundations.globals.constants.doctree
docs/sphinx/build/doctrees/resources/pages/api/foundations.guerilla.doctree
docs/sphinx/build/doctrees/resources/pages/api/foundations.io.doctree
docs/sphinx/build/doctrees/resources/pages/api/foundations.library.doctree
docs/sphinx/build/doctrees/resources/pages/api/foundations.namespace.doctree
docs/sphinx/build/doctrees/resources/pages/api/foundations.nodes.doctree
docs/sphinx/build/doctrees/resources/pages/api/foundations.parsers.doctree
docs/sphinx/build/doctrees/resources/pages/api/foundations.pkzip.doctree
docs/sphinx/build/doctrees/resources/pages/api/foundations.rotatingBackup.doctree
docs/sphinx/build/doctrees/resources/pages/api/foundations.shell.doctree
docs/sphinx/build/doctrees/resources/pages/api/foundations.strings.doctree
